crowe_b/__init__.py
crowe_b/cli.py
crowe_b-0.0.1.dist-info/METADATA
crowe_b-0.0.1.dist-info/WHEEL
crowe_b-0.0.1.dist-info/entry_points.txt
crowe_b-0.0.1.dist-info/RECORD
