Metadata-Version: 2.4
Name: crowe-b
Version: 0.0.1
Summary: Crowe-B CLI (chat via api.crowe-ai.com)
Requires-Python: >=3.8
Requires-Dist: requests>=2.28
